{"addAContact":"Ajouter un contact","accountNumber":"Numéro de compte","addASocialLink":"Ajouter un lien de réseau social","account":"Compte","activities":"Activités","award":"prix !","awards":"prix !","bankInfo":"Information bancaire","bankName":"Nom de la banque","bankNamePlaceholder":"Nom légal complet de votre banque","contactAdmin":"Envoyer un email à l'administrateur","contactContact":"Envoyer un email au contact","displayName":"Nom d'utilisateur","displayNamePlaceholder":"Nom d'utilisateur de votre organisation","ein":"Numéro d'identification de l'employeur :","emailAdmins":"Envoyer un email aux administrateurs","emailPlaceholder":"info@oursite.com","informationEmail":"Adresse e-mail d'information","informationNumber":"Numéro de téléphone d'information","link":"Lien","mailingAddress":"Adresse postale","mailingAddressPlaceholder":"101 East Main St, Charleston SC, USA","nameOnAccount":"Nom figurant sur le compte/Bénéficiaire acceptable","noOrgAwards":"Cette organisation n'a reçu aucune récompense","noOrgPayments":"Cette organisation n'a reçu aucun paiement pour","noOrgReports":"Cet organisme ne présente aucun rapport d’avancement","noOrgRequests":"Cette organisation n'a aucune demande pour","noPrograms":"Cette organisation n'a aucun programme lié.","noProjects":"Cette organisation n'a aucun projet.","numberOfAwards":"a reçu un total de","numberofProgressReports":"a un total de","offlineDonations":"Donations hors ligne","onlineDontations":"Donations en ligne","orgInfo":"Informations sur l'organisation","payment":"paiement !","paymentAlert1":"a reçu un total de","payments":"paiements !","phonePlaceholder":"(646) 580-6284","routingNumber":"Numéro de routage","shortMissionPlaceholder":"Courte description de votre organisation ou votre mission.","updateBankInfo":"Mettre les informations bancaires à jour","updateOrgInfo":"Mettre les informations de l'organisation à jour","webAddress":"Adresse du site","webAddressPlaceholder":"http://www.my-nonprofit.com"}